{"n8Fl1yHGUZk4ByzlbPeoJQ==":"naamloos-1-1999x1413.png","TF5u2lqDydS0IAUzJ+5yUA==":"wood-texture-1920x468.jpg","YzaL7S7m9msZYh2SjTMZUA==":"wood-141940_960_720-2-960x640.jpg","8NTHPs++Mxzxd8jhPaSTsg==":"logo2.png","NPuhEbAlJoarmEqpaY08+Q==":"mbr-709x1080.jpg","zSOMBfxEcw+nxJMLuKSaqg==":"naamloos-145-1999x1413.png","oy4g2p0DYMp6dFyOHCng8A==":"naamloos-146-1999x1413.png","27sIADp/IfEOyigZESZtMw==":"naamloos-147-1999x1413.png","BqthBDkAOOziU4whQiqFXQ==":"naamloos-148-1999x1413.png","oMqNLBzzVogcauTrAQrj2A==":"wood-texture-1920x468.png","wCwbwZiZzYoITmcJbLQTCw==":"webvera-1920x1080.jpg","G7ppxFmBiA01WEKusq5Vzg==":"01.jpg","2r+m+64ya5wkO3jYl4HQNA==":"03.jpg","F5znkk0Pi3u5mEQQA3IelQ==":"04.jpg","1IW715m7dQ2+ThBNpPUgOw==":"02.jpg","EHLXJz30A6msu4l2DcV76A==":"background2.jpg","sUbA98Bqa6Gfilbq/aLa/g==":"background1.jpg","VJfhqa70gNt01dbM86Iqsw==":"marleen%20habraken-4699x3133.jpg","ugMmcYZLUq4KErovNwcenQ==":"axelle%20hemels-5305x3537.jpg","Wk1ZCpVQkGB7unjLLj9Rig==":"sven%20goossens-5451x3634.jpg","0+tHAqukIpQMYC1LyLpOdg==":"veronika%20migryt-4459x2972.jpg","n+MGA4HztvSpmhWEKjxu7Q==":"marleen%20habraken-4699x3133.jpg","E4vuE/3qnEC0TyijZLxpYQ==":"axelle%20hemels-5305x3537.jpg","X106cZqWyeBRHOi4jBONvA==":"marleen%20habraken-4699x3133.jpg","oAJkfT5/T6xMuzA+Vsc2mQ==":"veronika%20migryt-4459x2972.jpg","uAqDh58hf7W8PSDbojcmWw==":"sven%20goossens-5451x3634.jpg","W1nqMBUbzYAqe8dcGWZURg==":"veronika%20migryt-4459x2972.jpg","EUsBRtWzYZPB/cI03s5nMw==":"marleen%20habraken-4699x3133.jpg","u5VZfJ/CBpCHJe+178V3Fg==":"marleen%20habraken-4699x3133.jpg","VeXYJnsncoqO2m5vtMdkog==":"focus%20snelbouwsteen%20beton-1999x1333.jpg","Z4hDnD2sHrzw2iasti+j9g==":"webvera-1-1920x1080.jpg","7epjpYCVjn+jC2w/umOH5A==":"brainstorm2%20(1)-1799x1287.jpg","IfvDX9isV6Q7AxxuOlAxvQ==":"brainstorm2%20(1)-1799x1287.jpg","W0qXzfvxa/UhGFaFM6kUcw==":"wood-141940_960_720-3-960x640.jpg","+cp8beH544Br6HJw2hNJOg==":"26235538_1564040343693051_1108167721_n-960x601.jpg","3/78xzlbo7RjIj/3BR27vw==":"26235538_1564040343693051_1108167721_n-1-960x601.jpg","dMy4NKj93Lr7JEAUASA17Q==":"background4.jpg","OS3RikbIDBfLPV83PUBedA==":"dsc-66-2000x1328.jpg","EaiPfbVwhE3FNlm83sFyiQ==":"dsc-71-1836x1347.jpg","qobUkoZwiBPOiD38l491wQ==":"dsc-72-1836x1347.jpg","KGtuwmB0/tquCbdLRKJjjQ==":"brainstorm2%20(1)-1799x1287.jpg","z7eArHWf6klqJDaOtfwZxQ==":"01-1.jpg","hW6gXX1qmYpsap35+uef2w==":"01-2.jpg","0sWw6LUDPaMsfc9YCoJXSg==":"barcode%20(2).gif","tMSSClHUfURZnHd+nGrPmA==":"barcode%20(1).gif","+mhliBbOR/frkxR1qm0bjA==":"barcode%20(1).gif","oYcyc15FF4Kyhfy6QRE/8g==":"barcode.gif","o17yOBm2zmb61oqsJvtCow==":"snelbouwsteen%20conceptidee%20def-2000x1414.jpg","OwwvQGNCZZU6SEGehg+NnA==":"2014-3-2000x2265.jpg","HyiHZQf8sK+CI6wqOFqh8g==":"2014-4-2000x2265.jpg"}